pypi_admin/__init__.py
pypi_admin/client.py
pypi_admin/collaborators.py
pypi_admin/events.py
pypi_admin/exceptions.py
pypi_admin/management.py
pypi_admin/projects.py
pypi_admin/releases.py
pypi_admin/session.py
pypi_admin/table.py
pypi_admin/tokens.py
pypi_admin/tests/__init__.py
pypi_admin-0.1.0.dist-info/LICENSE
pypi_admin-0.1.0.dist-info/METADATA
pypi_admin-0.1.0.dist-info/WHEEL
pypi_admin-0.1.0.dist-info/entry_points.txt
pypi_admin-0.1.0.dist-info/top_level.txt
pypi_admin-0.1.0.dist-info/RECORD
