Metadata-Version: 2.1
Name: pypi-admin
Version: 0.1.0
Summary: Pypi Warehoise API admin
Home-page: https://github.com/Nekmo/pypi-admin/
Author: Nekmo
Author-email: contacto@nekmo.com
License: MIT
Download-URL: https://github.com/Nekmo/pypi-admin/archive/master.zip
Keywords: pypi-admin
Platform: linux
Classifier: License :: OSI Approved :: MIT License
Classifier: Programming Language :: Python :: 3.7
Classifier: Programming Language :: Python :: 3.6
Classifier: Programming Language :: Python :: 3 :: Only
Classifier: Programming Language :: Python :: 3.5
Classifier: Programming Language :: Python :: 3.8
Classifier: Operating System :: POSIX
Classifier: Operating System :: POSIX :: Linux
Classifier: Natural Language :: English
Classifier: Development Status :: 5 - Production/Stable
Requires-Dist: click (>=6.0)
Requires-Dist: requests
Requires-Dist: beautifulsoup4
Requires-Dist: lxml
Requires-Dist: click-default-group
Requires-Dist: keyring
